traj_render/__init__.py
traj_render/renderer.py
traj_render-0.1.0.dist-info/METADATA
traj_render-0.1.0.dist-info/WHEEL
traj_render-0.1.0.dist-info/top_level.txt
traj_render-0.1.0.dist-info/RECORD
