Metadata-Version: 2.4
Name: traj-render
Version: 0.1.0
Summary: A high-performance OpenGL-based trajectory renderer
Author-email: Your Name <your.email@example.com>
Project-URL: Homepage, https://github.com/yourusername/traj-render
Classifier: Programming Language :: Python :: 3
Classifier: License :: OSI Approved :: MIT License
Classifier: Operating System :: OS Independent
Requires-Python: >=3.8
Requires-Dist: numpy
Requires-Dist: moderngl
Requires-Dist: imageio
Requires-Dist: imageio-ffmpeg
Requires-Dist: Pillow
